raftify-0.1.67.dist-info/METADATA
raftify-0.1.67.dist-info/WHEEL
raftify-0.1.67.dist-info/license_files/LICENSE
raftify/__init__.py
raftify/__init__.pyi
raftify/py.typed
raftify/raftify.cpython-312-darwin.so
raftify-0.1.67.dist-info/RECORD
