Metadata-Version: 2.3
Name: raftify
Version: 0.1.67
Classifier: Programming Language :: Rust
Classifier: Programming Language :: Python :: Implementation :: CPython
License-File: LICENSE
Summary: Experimental High level Raft framework
Keywords: raft,distributed-systems,consensus-algorithm,replication,distributed-database
Home-Page: https://github.com/lablup/raftify
Author: Lablup Inc.
License: Apache-2.0
Requires-Python: >=3.10
Project-URL: Source Code, https://github.com/lablup/raftify
